weibo_cli/__init__.py
weibo_cli/config.py
weibo_cli/exceptions.py
weibo_cli/utils.py
weibo_cli/weibo_client.py
weibo_cli/core/__init__.py
weibo_cli/core/auth.py
weibo_cli/core/client.py
weibo_cli/core/rate_limit.py
weibo_cli/core/retry.py
weibo_cli/models/__init__.py
weibo_cli/models/entities.py
weibo_cli/parsers/__init__.py
weibo_cli/parsers/comment.py
weibo_cli/parsers/post.py
weibo_cli/parsers/user.py
weibo_cli-1.0.4.dist-info/licenses/LICENSE
weibo_cli-1.0.4.dist-info/METADATA
weibo_cli-1.0.4.dist-info/WHEEL
weibo_cli-1.0.4.dist-info/top_level.txt
weibo_cli-1.0.4.dist-info/RECORD
